TrialPathfinder/__init__.py
TrialPathfinder/cohort_select.py
TrialPathfinder/emulate_trials.py
TrialPathfinder/shapley_computation.py
TrialPathfinder/utils.py
TrialPathfinder-1.1.0.dist-info/LICENSE
TrialPathfinder-1.1.0.dist-info/METADATA
TrialPathfinder-1.1.0.dist-info/WHEEL
TrialPathfinder-1.1.0.dist-info/top_level.txt
TrialPathfinder-1.1.0.dist-info/RECORD
