Metadata-Version: 2.1
Name: TrialPathfinder
Version: 1.1.0
Summary: Python library for systematic evaluation of clinical trial eligibility criteria.
Home-page: https://github.com/RuishanLiu/TrialPathfinder
Author: Ruishan Liu
Author-email: ruishan@stanford.edu
License: MIT
Platform: UNKNOWN
Requires-Dist: numpy
Requires-Dist: pandas
Requires-Dist: lifelines
Requires-Dist: sklearn
